{"qacxv1zhMUpDLBNE8xVfrA==":"mbr-1368x609.jpg","lLQWlqe+6QDI6/SiNC5tUA==":"img-2798-510x638.jpg","AyfixAr3sYqxcrIQp5sbDw==":"img-2799-510x638.jpg","XlQZBQwBguNpVsYeuGMweA==":"20150530_103240%20(1)-510x287.jpg","N3vEU56g4Gkr/EO80gAHLA==":"20150530_103240%20(1)-510x287.jpg","X4Bpsfe3uByNTRYpn9ghEg==":"20150530_104548%20(1)-510x287.jpg","vGWQJGLlsnxyNyVfVg/qPQ==":"img-2591-510x1020.jpg","4v9lgL7fX0zD7IYKRc7HBA==":"20150530_103240%20(1)-510x287.jpg","sM0nE+mhLgFdBb8K2yJC2g==":"give%20thanks-510x637.jpg","bD8WAgdvNZZxQlqlsADFSQ==":"img950185-510x617.jpg","TDutvFY9PguGcl/HpJq6Ig==":"img-1959-510x516.jpg","C9M/gZ5TDnXlYB87WkPP4g==":"paige%20photo-510x680.jpg"}